pytestlab/__init__.py
pytestlab/_log.py
pytestlab/bench.py
pytestlab/cli.py
pytestlab/errors.py
pytestlab/analysis/__init__.py
pytestlab/analysis/fft.py
pytestlab/analysis/fr_analysis.py
pytestlab/common/__init__.py
pytestlab/common/enums.py
pytestlab/common/health.py
pytestlab/compliance/__init__.py
pytestlab/compliance/audit.py
pytestlab/compliance/patch.py
pytestlab/compliance/signature.py
pytestlab/compliance/tsa.py
pytestlab/config/__init__.py
pytestlab/config/_mixins.py
pytestlab/config/accuracy.py
pytestlab/config/base.py
pytestlab/config/bench_config.py
pytestlab/config/bench_loader.py
pytestlab/config/config.py
pytestlab/config/dc_active_load_config.py
pytestlab/config/instrument_config.py
pytestlab/config/loader.py
pytestlab/config/multimeter_config.py
pytestlab/config/oscilloscope_config.py
pytestlab/config/power_meter_config.py
pytestlab/config/power_supply_config.py
pytestlab/config/spectrum_analyzer_config.py
pytestlab/config/virtual_instrument_config.py
pytestlab/config/vna_config.py
pytestlab/config/waveform_generator_config.py
pytestlab/experiments/__init__.py
pytestlab/experiments/database.py
pytestlab/experiments/experiments.py
pytestlab/experiments/results.py
pytestlab/experiments/sweep.py
pytestlab/gui/__init__.py
pytestlab/gui/async_utils.py
pytestlab/gui/builder.py
pytestlab/instruments/AutoInstrument.py
pytestlab/instruments/DCActiveLoad.py
pytestlab/instruments/Multimeter.py
pytestlab/instruments/Oscilloscope.py
pytestlab/instruments/PowerMeter.py
pytestlab/instruments/PowerSupply.py
pytestlab/instruments/SpectrumAnalyser.py
pytestlab/instruments/VectorNetworkAnalyser.py
pytestlab/instruments/VirtualInstrument.py
pytestlab/instruments/WaveformGenerator.py
pytestlab/instruments/__init__.py
pytestlab/instruments/instrument.py
pytestlab/instruments/scpi_engine.py
pytestlab/instruments/backends/__init__.py
pytestlab/instruments/backends/async_visa_backend.py
pytestlab/instruments/backends/lamb.py
pytestlab-0.2.1.dist-info/METADATA
pytestlab-0.2.1.dist-info/WHEEL
pytestlab-0.2.1.dist-info/entry_points.txt
pytestlab-0.2.1.dist-info/RECORD
