Metadata-Version: 2.4
Name: pytestlab
Version: 0.2.1
Summary: Scientific test & measurement toolbox
Author-email: Emmanuel Olowe <e.a.olowe@ed.ac.uk>
License: MIT
Requires-Python: >=3.11
Requires-Dist: aiofiles
Requires-Dist: cryptography
Requires-Dist: httpx
Requires-Dist: numpy
Requires-Dist: pillow
Requires-Dist: polars
Requires-Dist: pydantic
Requires-Dist: pyscpi
Requires-Dist: pyusb
Requires-Dist: pyvisa
Requires-Dist: pyyaml
Requires-Dist: requests
Requires-Dist: tqdm
Requires-Dist: typer
Requires-Dist: uncertainties
Provides-Extra: dev
Requires-Dist: aiofiles; extra == 'dev'
Requires-Dist: httpx; extra == 'dev'
Requires-Dist: mypy; extra == 'dev'
Requires-Dist: pre-commit; extra == 'dev'
Requires-Dist: pytest; extra == 'dev'
Requires-Dist: pytest-cov; extra == 'dev'
Requires-Dist: ruff; extra == 'dev'
Provides-Extra: docs
Requires-Dist: ghp-import>=2.1.0; extra == 'docs'
Requires-Dist: matplotlib>=3.10.3; extra == 'docs'
Requires-Dist: mkdocs-autorefs>=1.4.2; extra == 'docs'
Requires-Dist: mkdocs-awesome-pages-plugin>=2.10.1; extra == 'docs'
Requires-Dist: mkdocs-git-revision-date-localized-plugin>=1.4.7; extra == 'docs'
Requires-Dist: mkdocs-i18n>=0.4.6; extra == 'docs'
Requires-Dist: mkdocs-jupyter>=0.25.1; extra == 'docs'
Requires-Dist: mkdocs-material-extensions>=1.3.1; extra == 'docs'
Requires-Dist: mkdocs-material>=9.6.15; extra == 'docs'
Requires-Dist: mkdocs>=1.6.1; extra == 'docs'
Requires-Dist: mkdocstrings[python]>=0.29.1; extra == 'docs'
Requires-Dist: plotly>=6.2.0; extra == 'docs'
Requires-Dist: pymdown-extensions>=10.16; extra == 'docs'
Requires-Dist: watchdog>=6.0.0; extra == 'docs'
Provides-Extra: full
Requires-Dist: matplotlib; extra == 'full'
Requires-Dist: plotly; extra == 'full'
Requires-Dist: pydantic; extra == 'full'
Requires-Dist: pyvisa-sim; extra == 'full'
Requires-Dist: uncertainties; extra == 'full'
Provides-Extra: plot
Requires-Dist: matplotlib; extra == 'plot'
Requires-Dist: plotly; extra == 'plot'
